{
  "project_info": {
    "project_number": "788847219767",
    "firebase_url": "https://sakyo-aldebaran.firebaseio.com",
    "project_id": "sakyo-aldebaran",
    "storage_bucket": "sakyo-aldebaran.appspot.com"
  },
  "client": [
    {
      "client_info": {
        "mobilesdk_app_id": "1:788847219767:android:4dd20b56f6a71f42b71bb2",
        "android_client_info": {
          "package_name": "com.sakyo.azurcompendium"
        }
      },
      "oauth_client": [
        {
          "client_id": "788847219767-6qh8eeg0h4uknhl188irm3s2lk4ovhlf.apps.googleusercontent.com",
          "client_type": 3
        }
      ],
      "api_key": [
        {
          "current_key": "AIzaSyDHR1ZWnThmcd-ZqlxbRIRbI9JG1cpJH9E"
        }
      ],
      "services": {
        "appinvite_service": {
          "other_platform_oauth_client": [
            {
              "client_id": "788847219767-6qh8eeg0h4uknhl188irm3s2lk4ovhlf.apps.googleusercontent.com",
              "client_type": 3
            }
          ]
        }
      }
    }
  ],
  "configuration_version": "1"
}